[{"name":"Región de Valparaíso","iso":"VS","fips":"01","admin":"01","reference":{}},{"name":"Región de Tarapacá","iso":"TA","fips":"15","admin":"15","reference":{}},{"name":"Región Metropolitana de Santiago","iso":"RM","fips":"12","admin":"12","reference":{}},{"name":"Región del Maule","iso":"ML","fips":"11","admin":"11","reference":{}},{"name":"Región de los Lagos","iso":"LL","fips":"14","admin":"14","reference":{}},{"name":"Región del Libertador General Bernardo O’Higgins","iso":"LI","fips":"08","admin":"08","reference":{}},{"name":"Región de Coquimbo","iso":"CO","fips":"07","admin":"07","reference":{}},{"name":"Región del Bío-Bío","iso":"BI","fips":"06","admin":"06","reference":{}},{"name":"Región de Atacama","iso":"AT","fips":"05","admin":"05","reference":{}},{"name":"Región de la Araucanía","iso":"AR","fips":"04","admin":"04","reference":{}},{"name":"Región de Antofagasta","iso":"AN","fips":"03","admin":"03","reference":{}},{"name":"Región de Aysén","iso":"AI","fips":"02","admin":"02","reference":{}},{"name":"Región de Magallanes y de la Antártica Chilena","iso":"MA","fips":"10","admin":"10","reference":{}},{"name":"Región de Arica y Parinacota","iso":"AP","fips":"16","admin":"16","reference":{}},{"name":"Región de Los Ríos","iso":"LR","fips":"17","admin":"17","reference":{}}]