[{"name":"祖省","iso":"ZO","fips":"18","admin":"18","reference":{}},{"name":"韋梅省","iso":"OU","fips":"16","admin":"16","reference":{}},{"name":"莫諾省","iso":"MO","fips":"15","admin":"15","reference":{}},{"name":"博爾古省","iso":"BO","fips":"10","admin":"10","reference":{}},{"name":"大西洋省","iso":"AQ","fips":"09","admin":"09","reference":{}},{"name":"阿塔科拉省","iso":"AK","fips":"08","admin":"08","reference":{}},{"name":"阿黎博里省","iso":"AL","fips":"07","admin":"07","reference":{}},{"name":"丘陵省","iso":"CO","fips":"11","admin":"11","reference":{}},{"name":"庫福省","iso":"KO","fips":"12","admin":"12","reference":{}},{"name":"峽谷省","iso":"DO","fips":"13","admin":"13","reference":{}},{"name":"濱海省","iso":"LI","fips":"14","admin":"14","reference":{}},{"name":"高原省","iso":"PL","fips":"17","admin":"17","reference":{}}]