[{"name":"Distretto di Edineț","iso":"ED","fips":"73","admin":"73","reference":{}},{"name":"Distretto di Ungheni","iso":"UN","fips":"92","admin":"92","reference":{}},{"name":"Distretto di Telenești","iso":"TE","fips":"91","admin":"91","reference":{}},{"name":"Distretto di Taraclia","iso":"TA","fips":"90","admin":"90","reference":{}},{"name":"Distretto di Ștefan Vodă","iso":"SV","fips":"88","admin":"88","reference":{}},{"name":"Distretto di Strășeni","iso":"ST","fips":"89","admin":"89","reference":{}},{"name":"Distretto di Soroca","iso":"SO","fips":"87","admin":"87","reference":{}},{"name":"Distretto di Rîșcani","iso":"RI","fips":"84","admin":"84","reference":{}},{"name":"Distretto di Rezina","iso":"RE","fips":"83","admin":"83","reference":{}},{"name":"Distretto di Orhei","iso":"OR","fips":"82","admin":"82","reference":{}},{"name":"Distretto di Ocnița","iso":"OC","fips":"81","admin":"81","reference":{}},{"name":"Distretto di Anenii Noi","iso":"AN","fips":"59","admin":"59","reference":{}},{"name":"Distretto di Nisporeni","iso":"NI","fips":"80","admin":"80","reference":{}},{"name":"Distretto di Leova","iso":"LE","fips":"79","admin":"79","reference":{}},{"name":"Distretto di Sîngerei","iso":"SI","fips":"85","admin":"85","reference":{}},{"name":"Distretto di Criuleni","iso":"CR","fips":"69","admin":"69","reference":{}},{"name":"Distretto di Ialoveni","iso":"IA","fips":"78","admin":"78","reference":{}},{"name":"Chișinău","iso":"CU","fips":"57","admin":"57","reference":{}},{"name":"Distretto di Căușeni","iso":"CS","fips":"67","admin":"67","reference":{}},{"name":"Distretto di Cantemir","iso":"CT","fips":"65","admin":"65","reference":{}},{"name":"Distretto di Călărași","iso":"CL","fips":"66","admin":"66","reference":{}},{"name":"Distretto di Cahul","iso":"CA","fips":"64","admin":"64","reference":{}},{"name":"Distretto di Glodeni","iso":"GL","fips":"76","admin":"76","reference":{}},{"name":"Distretto di Florești","iso":"FL","fips":"75","admin":"75","reference":{}},{"name":"Distretto di Fălești","iso":"FA","fips":"74","admin":"74","reference":{}},{"name":"Distretto di Dubăsari","iso":"DU","fips":"72","admin":"72","reference":{}},{"name":"Distretto di Drochia","iso":"DR","fips":"71","admin":"71","reference":{}},{"name":"Distretto di Dondușeni","iso":"DO","fips":"70","admin":"70","reference":{}},{"name":"Distretto di Cimișlia","iso":"CM","fips":"68","admin":"68","reference":{}},{"name":"Distretto di Briceni","iso":"BR","fips":"63","admin":"63","reference":{}},{"name":"Distretto di Basarabeasca","iso":"BS","fips":"61","admin":"61","reference":{}},{"name":"Distretto di Hîncești","iso":"HI","fips":"77","admin":"77","reference":{}},{"name":"Distretto di Șoldănești","iso":"SD","fips":"86","admin":"86","reference":{}},{"name":"Transnistria","iso":"SN","fips":"58","admin":"58","reference":{}},{"name":"Gagauzia","iso":"GA","fips":"51","admin":"51","reference":{}},{"name":"Tighina","iso":"BD","fips":"62","admin":"62","reference":{}},{"name":"Bălți","iso":"BA","fips":"60","admin":"60","reference":{}}]