[{"name":"Zulia","iso":"V","fips":"23","admin":"23","reference":{}},{"name":"Yaracuy","iso":"U","fips":"22","admin":"22","reference":{}},{"name":"Trujillo","iso":"T","fips":"21","admin":"21","reference":{}},{"name":"Táchira","iso":"S","fips":"20","admin":"20","reference":{}},{"name":"Sucre","iso":"R","fips":"19","admin":"19","reference":{}},{"name":"Portuguesa","iso":"P","fips":"18","admin":"18","reference":{}},{"name":"Nueva Esparta","iso":"O","fips":"17","admin":"17","reference":{}},{"name":"Monagas","iso":"N","fips":"16","admin":"16","reference":{}},{"name":"Miranda","iso":"M","fips":"15","admin":"15","reference":{}},{"name":"Mérida","iso":"L","fips":"14","admin":"14","reference":{}},{"name":"Lara","iso":"K","fips":"13","admin":"13","reference":{}},{"name":"Guárico","iso":"J","fips":"12","admin":"12","reference":{}},{"name":"Federal Dependencies of Venezuela","iso":"W","fips":"24","admin":"24","reference":{}},{"name":"Capital","iso":"A","fips":"25","admin":"25","reference":{}},{"name":"Falcón","iso":"I","fips":"11","admin":"11","reference":{}},{"name":"Delta Amacuro","iso":"Y","fips":"09","admin":"09","reference":{}},{"name":"Cojedes","iso":"H","fips":"08","admin":"08","reference":{}},{"name":"Carabobo","iso":"G","fips":"07","admin":"07","reference":{}},{"name":"Bolivar","iso":"F","fips":"06","admin":"06","reference":{}},{"name":"Barinas","iso":"E","fips":"05","admin":"05","reference":{}},{"name":"Aragua","iso":"D","fips":"04","admin":"04","reference":{}},{"name":"Apure","iso":"C","fips":"03","admin":"03","reference":{}},{"name":"Anzoátegui","iso":"B","fips":"02","admin":"02","reference":{}},{"name":"Amazonas","iso":"Z","fips":"01","admin":"01","reference":{}},{"name":"Vargas","iso":"X","fips":"26","admin":"26","reference":{}}]