[{"name":"Gobernación de Tartus","iso":"TA","fips":"14","admin":"14","reference":{}},{"name":"Damasco","iso":"DI","fips":"13","admin":"13","reference":{}},{"name":"Gobernación de Idlib","iso":"ID","fips":"12","admin":"12","reference":{}},{"name":"Gobernación de Homs","iso":"HI","fips":"11","admin":"11","reference":{}},{"name":"Gobernación de Hama","iso":"HM","fips":"10","admin":"10","reference":{}},{"name":"Gobernación de Alepo","iso":"HL","fips":"09","admin":"09","reference":{}},{"name":"Gobernación de la Campiña de Damasco","iso":"RD","fips":"08","admin":"08","reference":{}},{"name":"Gobernación de Deir ez-Zor","iso":"DY","fips":"07","admin":"07","reference":{}},{"name":"Gobernación de Dar'a","iso":"DR","fips":"06","admin":"06","reference":{}},{"name":"Gobernación de Sueida","iso":"SU","fips":"05","admin":"05","reference":{}},{"name":"Gobernación de Raqqa","iso":"RA","fips":"04","admin":"04","reference":{}},{"name":"Gobernación de Quneitra","iso":"QU","fips":"03","admin":"03","reference":{}},{"name":"Gobernación de Latakia","iso":"LA","fips":"02","admin":"02","reference":{}},{"name":"Gobernación de Hasaka","iso":"HA","fips":"01","admin":"01","reference":{}}]