[{"name":"울산광역시","iso":"31","fips":"21","admin":"21","reference":{}},{"name":"대전광역시","iso":"30","fips":"19","admin":"19","reference":{}},{"name":"대구광역시","iso":"27","fips":"15","admin":"15","reference":{}},{"name":"서울특별시","iso":"11","fips":"11","admin":"11","reference":{}},{"name":"부산광역시","iso":"26","fips":"10","admin":"10","reference":{}},{"name":"경상북도","iso":"47","fips":"14","admin":"14","reference":{}},{"name":"경기도","iso":"41","fips":"13","admin":"13","reference":{}},{"name":"광주광역시","iso":"29","fips":"18","admin":"18","reference":{}},{"name":"강원도","iso":"42","fips":"06","admin":"06","reference":{}},{"name":"인천광역시","iso":"28","fips":"12","admin":"12","reference":{}},{"name":"충청남도","iso":"44","fips":"17","admin":"17","reference":{}},{"name":"충청북도","iso":"43","fips":"05","admin":"05","reference":{}},{"name":"전라남도","iso":"46","fips":"16","admin":"16","reference":{}},{"name":"전라북도","iso":"45","fips":"03","admin":"03","reference":{}},{"name":"제주특별자치도","iso":"49","fips":"01","admin":"01","reference":{}},{"name":"경상남도","iso":"48","fips":"20","admin":"20","reference":{}},{"name":"세종특별자치시","iso":"22","fips":"22","admin":"22","reference":{}}]