[{"name":"Zou","iso":"ZO","fips":"18","admin":"18","reference":{}},{"name":"Ouémé","iso":"OU","fips":"16","admin":"16","reference":{}},{"name":"Mono","iso":"MO","fips":"15","admin":"15","reference":{}},{"name":"Borgou","iso":"BO","fips":"10","admin":"10","reference":{}},{"name":"Atlantique","iso":"AQ","fips":"09","admin":"09","reference":{}},{"name":"Atacora","iso":"AK","fips":"08","admin":"08","reference":{}},{"name":"Alibori","iso":"AL","fips":"07","admin":"07","reference":{}},{"name":"Collines","iso":"CO","fips":"11","admin":"11","reference":{}},{"name":"Couffo","iso":"KO","fips":"12","admin":"12","reference":{}},{"name":"Donga","iso":"DO","fips":"13","admin":"13","reference":{}},{"name":"Littoral","iso":"LI","fips":"14","admin":"14","reference":{}},{"name":"Plateau","iso":"PL","fips":"17","admin":"17","reference":{}}]