[{"name":"Zinder Region","iso":"7","fips":"07","admin":"07","reference":{}},{"name":"Tahoua Region","iso":"5","fips":"06","admin":"06","reference":{}},{"name":"Maradi Region","iso":"4","fips":"04","admin":"04","reference":{}},{"name":"Dosso Region","iso":"3","fips":"03","admin":"03","reference":{}},{"name":"Diffa Region","iso":"2","fips":"02","admin":"02","reference":{}},{"name":"Agadez Region","iso":"1","fips":"01","admin":"01","reference":{}},{"name":"Tillabéri Region","iso":"6","fips":"09","admin":"09","reference":{}},{"name":"Niamey","iso":"8","fips":"08","admin":"08","reference":{}}]