[{"name":"Région de Tanintharyi","iso":"05","fips":"12","admin":"12","reference":{}},{"name":"État Shan","iso":"17","fips":"11","admin":"11","reference":{}},{"name":"Région de Sagaing","iso":"01","fips":"10","admin":"10","reference":{}},{"name":"Région de Yangon","iso":"06","fips":"17","admin":"17","reference":{}},{"name":"État d'Arakan","iso":"16","fips":"01","admin":"01","reference":{}},{"name":"Région de Bago","iso":"02","fips":"16","admin":"16","reference":{}},{"name":"État Môn","iso":"15","fips":"13","admin":"13","reference":{}},{"name":"Région de Mandalay","iso":"04","fips":"08","admin":"08","reference":{}},{"name":"Région de Magway","iso":"03","fips":"15","admin":"15","reference":{}},{"name":"État de Kayah","iso":"12","fips":"06","admin":"06","reference":{}},{"name":"État Karen","iso":"13","fips":"05","admin":"05","reference":{}},{"name":"État Kachin","iso":"11","fips":"04","admin":"04","reference":{}},{"name":"Région d'Ayeyarwady","iso":"07","fips":"03","admin":"03","reference":{}},{"name":"État Chin","iso":"14","fips":"02","admin":"02","reference":{}},{"name":"Nay Pyi Taw","iso":"18","fips":"18","admin":"18","reference":{}}]