[{"name":"Люблинское воеводство","iso":"06","fips":"75","admin":"75","reference":{}},{"name":"Малопольское воеводство","iso":"12","fips":"77","admin":"77","reference":{}},{"name":"Мазовецкое воеводство","iso":"14","fips":"78","admin":"78","reference":{}},{"name":"Подкарпатское воеводство","iso":"18","fips":"80","admin":"80","reference":{}},{"name":"Подляское воеводство","iso":"20","fips":"81","admin":"81","reference":{}},{"name":"Свентокшиское воеводство","iso":"26","fips":"84","admin":"84","reference":{}},{"name":"Варминьско-Мазурское","iso":"28","fips":"85","admin":"85","reference":{}},{"name":"Нижнесилезское воеводство","iso":"02","fips":"72","admin":"72","reference":{}},{"name":"Лодзинское воеводство","iso":"10","fips":"74","admin":"74","reference":{}},{"name":"Любушское воеводство","iso":"08","fips":"76","admin":"76","reference":{}},{"name":"Опольское воеводство","iso":"16","fips":"79","admin":"79","reference":{}},{"name":"Поморское воеводство","iso":"22","fips":"82","admin":"82","reference":{}},{"name":"Силезское воеводство","iso":"24","fips":"83","admin":"83","reference":{}},{"name":"Великопольское воеводство","iso":"30","fips":"86","admin":"86","reference":{}},{"name":"Западно-Поморское воеводство","iso":"32","fips":"87","admin":"87","reference":{}},{"name":"Куявско-Поморское воеводство","iso":"04","fips":"73","admin":"73","reference":{}}]