[{"name":"Karakalpakstan","iso":"QR","fips":"09","admin":"09","reference":{}},{"name":"Surxondaryo Province","iso":"SU","fips":"12","admin":"12","reference":{}},{"name":"Samarqand Province","iso":"SA","fips":"10","admin":"10","reference":{}},{"name":"Qashqadaryo Province","iso":"QA","fips":"08","admin":"08","reference":{}},{"name":"Bukhara Province","iso":"BU","fips":"02","admin":"02","reference":{}},{"name":"Tashkent Province","iso":"TO","fips":"14","admin":"14","reference":{}},{"name":"Tashkent","iso":"TK","fips":"13","admin":"13","reference":{}},{"name":"Sirdaryo Province","iso":"SI","fips":"16","admin":"16","reference":{}},{"name":"Navoiy Province","iso":"NW","fips":"07","admin":"07","reference":{}},{"name":"Namangan Province","iso":"NG","fips":"06","admin":"06","reference":{}},{"name":"Xorazm Province","iso":"XO","fips":"05","admin":"05","reference":{}},{"name":"Jizzakh Province","iso":"JI","fips":"15","admin":"15","reference":{}},{"name":"Fergana Province","iso":"FA","fips":"03","admin":"03","reference":{}},{"name":"Andijan Province","iso":"AN","fips":"01","admin":"01","reference":{}}]