[{"name":"通巴利區","iso":"TO","fips":"07","admin":"07","reference":{}},{"name":"基納拉區","iso":"QU","fips":"02","admin":"02","reference":{}},{"name":"奧約區","iso":"OI","fips":"04","admin":"04","reference":{}},{"name":"加布區","iso":"GA","fips":"10","admin":"10","reference":{}},{"name":"卡謝烏區","iso":"CA","fips":"06","admin":"06","reference":{}},{"name":"博拉馬區","iso":"BL","fips":"05","admin":"05","reference":{}},{"name":"比绍","iso":"BS","fips":"11","admin":"11","reference":{}},{"name":"比翁博區","iso":"BM","fips":"12","admin":"12","reference":{}},{"name":"巴法塔區","iso":"BA","fips":"01","admin":"01","reference":{}}]