[{"name":"ياماناشي","iso":"19","fips":"46","admin":"46","reference":{}},{"name":"ياماغوتشي","iso":"35","fips":"45","admin":"45","reference":{}},{"name":"واكاياما","iso":"30","fips":"43","admin":"43","reference":{}},{"name":"توياما","iso":"16","fips":"42","admin":"42","reference":{}},{"name":"توتوري","iso":"31","fips":"41","admin":"41","reference":{}},{"name":"طوكيو","iso":"13","fips":"40","admin":"40","reference":{}},{"name":"توكوشيما","iso":"36","fips":"39","admin":"39","reference":{}},{"name":"توتشيغي","iso":"09","fips":"38","admin":"38","reference":{}},{"name":"شيزوكا","iso":"22","fips":"37","admin":"37","reference":{}},{"name":"شيمانه","iso":"32","fips":"36","admin":"36","reference":{}},{"name":"شيغا","iso":"25","fips":"35","admin":"35","reference":{}},{"name":"سايتاما","iso":"11","fips":"34","admin":"34","reference":{}},{"name":"ساغا","iso":"41","fips":"33","admin":"33","reference":{}},{"name":"أوساكا","iso":"27","fips":"32","admin":"32","reference":{}},{"name":"أوكيناوا","iso":"47","fips":"47","admin":"47","reference":{}},{"name":"أوكاياما","iso":"33","fips":"31","admin":"31","reference":{}},{"name":"أويتا","iso":"44","fips":"30","admin":"30","reference":{}},{"name":"نييغاتا","iso":"15","fips":"29","admin":"29","reference":{}},{"name":"نارا","iso":"29","fips":"28","admin":"28","reference":{}},{"name":"ناغاساكي","iso":"42","fips":"27","admin":"27","reference":{}},{"name":"ناغانو","iso":"20","fips":"26","admin":"26","reference":{}},{"name":"ميازاكي","iso":"45","fips":"25","admin":"25","reference":{}},{"name":"ميه","iso":"24","fips":"23","admin":"23","reference":{}},{"name":"كيوتو","iso":"26","fips":"22","admin":"22","reference":{}},{"name":"كوماموتو","iso":"43","fips":"21","admin":"21","reference":{}},{"name":"كوتشي","iso":"39","fips":"20","admin":"20","reference":{}},{"name":"كاناغاوا","iso":"14","fips":"19","admin":"19","reference":{}},{"name":"كاغوشيما","iso":"46","fips":"18","admin":"18","reference":{}},{"name":"كاغاوا","iso":"37","fips":"17","admin":"17","reference":{}},{"name":"إيشيكاوا","iso":"17","fips":"15","admin":"15","reference":{}},{"name":"هيوغو","iso":"28","fips":"13","admin":"13","reference":{}},{"name":"هيروشيما","iso":"34","fips":"11","admin":"11","reference":{}},{"name":"غونما","iso":"10","fips":"10","admin":"10","reference":{}},{"name":"غيفو","iso":"21","fips":"09","admin":"09","reference":{}},{"name":"فوكوكا","iso":"40","fips":"07","admin":"07","reference":{}},{"name":"فوكوي","iso":"18","fips":"06","admin":"06","reference":{}},{"name":"إهيمه","iso":"38","fips":"05","admin":"05","reference":{}},{"name":"آيتشي","iso":"23","fips":"01","admin":"01","reference":{}},{"name":"ياماغاتا","iso":"06","fips":"44","admin":"44","reference":{}},{"name":"مياغي","iso":"04","fips":"24","admin":"24","reference":{}},{"name":"إيواته","iso":"03","fips":"16","admin":"16","reference":{}},{"name":"إيباراكي","iso":"08","fips":"14","admin":"14","reference":{}},{"name":"فوكوشيما","iso":"07","fips":"08","admin":"08","reference":{}},{"name":"تشيبا","iso":"12","fips":"04","admin":"04","reference":{}},{"name":"أكيتا","iso":"05","fips":"02","admin":"02","reference":{}},{"name":"هوكايدو","iso":"01","fips":"12","admin":"12","reference":{}},{"name":"آوموري","iso":"02","fips":"03","admin":"03","reference":{}}]